sitegenlib/__init__.py
sitegenlib/__main__.py
sitegenlib/_vars.py
sitegenlib/document.py
sitegenlib/errors.py
sitegenlib/parsers.py
sitegenlib/parsing.py
sitegenlib/simple.py
sitegenlib/util.py
sitegenlib/__pycache__/__init__.cpython-38.pyc
sitegenlib/model/__init__.py
sitegenlib/model/document.py
sitegenlib/template/__init__.py
sitegenlib/template/build.py
sitegenlib/template/engine.py
sitegenlib/template/util.py
sitegenlib/template/__pycache__/__init__.cpython-38.pyc
sitegenlib/template/__pycache__/util.cpython-38.pyc
iwg-0.1.2.dist-info/METADATA
iwg-0.1.2.dist-info/WHEEL
iwg-0.1.2.dist-info/top_level.txt
iwg-0.1.2.dist-info/RECORD
