Metadata-Version: 2.1
Name: iwg
Version: 0.1.2
Summary: An in-house website generator
Home-page: http://github.com/bozdogan/iwg
Author: Bora Ozdogan
Author-email: boraozdogan99@gmail.com
License: MIT
Platform: UNKNOWN
Classifier: Development Status :: 1 - Planning
Classifier: Environment :: Console
Classifier: Intended Audience :: Developers
Classifier: License :: OSI Approved :: MIT License
Classifier: Programming Language :: Python :: 3.8
Classifier: Topic :: Software Development :: Code Generators
Requires-Dist: toml
Requires-Dist: pyyaml
Requires-Dist: markdown (~=3.3.6)
Provides-Extra: dev
